johann_plugin_example/__init__.py
johann_plugin_example/config.py
johann_plugin_example/tasks.py
johann_plugin_example/scores/simple_example_1.yml
johann_plugin_example-0.1.0a0.dist-info/AUTHORS
johann_plugin_example-0.1.0a0.dist-info/LICENSE
johann_plugin_example-0.1.0a0.dist-info/METADATA
johann_plugin_example-0.1.0a0.dist-info/WHEEL
johann_plugin_example-0.1.0a0.dist-info/top_level.txt
johann_plugin_example-0.1.0a0.dist-info/RECORD
