Metadata-Version: 2.1
Name: johann-plugin-example
Version: 0.1.0a0
Summary: An example of a plugin for Johann
Home-page: https://github.com/johannsdg/johann-plugin-example
Author: Jeffrey James
Author-email: lobotmcj@gmail.com
License: BSD
Platform: UNKNOWN
Classifier: Development Status :: 3 - Alpha
Classifier: License :: OSI Approved :: BSD License
Classifier: Programming Language :: Python :: 3
Classifier: Programming Language :: Python :: 3 :: Only
Classifier: Operating System :: POSIX :: Linux
Requires-Python: >=3.6, <4
Requires-Dist: johann (>=0.2.0a0)
Requires-Dist: numpy
